hugepagination/__init__.py
hugepagination/pagination.py
hugepagination/views.py
django_hugepagination-1.0.2.dist-info/LICENSE
django_hugepagination-1.0.2.dist-info/METADATA
django_hugepagination-1.0.2.dist-info/WHEEL
django_hugepagination-1.0.2.dist-info/top_level.txt
django_hugepagination-1.0.2.dist-info/RECORD
