Metadata-Version: 2.1
Name: django-hugepagination
Version: 1.0.2
Summary: django huge pagination
Home-page: https://github.com/tangdyy/django-hugepagination
Author: Tang dayong
Author-email: tangdyy@126.com
Classifier: Programming Language :: Python :: 3
Classifier: License :: OSI Approved :: MIT License
Classifier: Operating System :: OS Independent
Requires-Python: >=3.6
License-File: LICENSE
Requires-Dist: django >=2.2.0
Requires-Dist: djangorestframework >=3.1.0
Requires-Dist: django-filter >=2.2.0
